py2casefold/CaseFolding.txt
py2casefold/VERSION
py2casefold/__init__.py
py2casefold-0.2.0.dist-info/DESCRIPTION.rst
py2casefold-0.2.0.dist-info/METADATA
py2casefold-0.2.0.dist-info/RECORD
py2casefold-0.2.0.dist-info/WHEEL
py2casefold-0.2.0.dist-info/metadata.json
py2casefold-0.2.0.dist-info/top_level.txt
