Metadata-Version: 2.0
Name: py2casefold
Version: 0.2.0
Summary: Unicode casefold support for python 2.
Home-page: https://github.com/rwarren/py2casefold
Author: Russell Warren
Author-email: russ@perspexis.com
License: BSD
Keywords: unicode casefold
Platform: UNKNOWN
Classifier: Development Status :: 3 - Alpha
Classifier: Intended Audience :: Developers
Classifier: Topic :: Software Development
Classifier: Topic :: Software Development :: User Interfaces
Classifier: Topic :: Software Development :: Libraries :: Python Modules
Classifier: License :: OSI Approved :: BSD License
Classifier: Programming Language :: Python
Classifier: Programming Language :: Python :: 2.6
Classifier: Programming Language :: Python :: 2.7
Classifier: Operating System :: OS Independent
